bigwood/__init__.py
bigwood/bin/getip.py
bigwood/config.py
bigwood/data/__init__.py
bigwood/data/plotting/__init__.py
bigwood/data/plotting/conf.py
bigwood/data/plotting/graphs.py
bigwood/data/plotting/layout.py
bigwood/data/plotting/utils.py
bigwood/data/utilities.py
bigwood/data/utils.py
bigwood/files.py
bigwood/network.py
bigwood/test/test_files.py
bigwood-0.0.9.dist-info/entry_points.txt
bigwood-0.0.9.dist-info/WHEEL
bigwood-0.0.9.dist-info/METADATA
bigwood-0.0.9.dist-info/RECORD
